opentext2sql/__init__.py
opentext2sql/agent/__init__.py
opentext2sql/agent/create_agent.py
opentext2sql/agent/prompt.py
opentext2sql/agent/tool_function.py
opentext2sql/base/__init__.py
opentext2sql/base/base.py
opentext2sql/base/build_train_data.py
opentext2sql/base/excel_data_get.py
opentext2sql/base/get_table_schema.py
opentext2sql/base/group_tables_graph.py
opentext2sql/chroma/__init__.py
opentext2sql/chroma/chromadb_vector.py
opentext2sql-0.1.0.dist-info/licenses/LICENSE
opentext2sql-0.1.0.dist-info/METADATA
opentext2sql-0.1.0.dist-info/WHEEL
opentext2sql-0.1.0.dist-info/top_level.txt
opentext2sql-0.1.0.dist-info/RECORD
