Metadata-Version: 2.4
Name: opentext2sql
Version: 0.1.0
Summary: A simple math utilities package
Author: iooo2333
Classifier: Programming Language :: Python :: 3
Classifier: License :: OSI Approved :: MIT License
Classifier: Operating System :: OS Independent
Requires-Python: >=3.6
License-File: LICENSE
Requires-Dist: langchain_core
Requires-Dist: langgraph
Requires-Dist: Pillow
Requires-Dist: sqlparse
Requires-Dist: pandas
Requires-Dist: chromadb
Requires-Dist: sqlalchemy
Requires-Dist: langchain_openai
Requires-Dist: psycopg2
Dynamic: author
Dynamic: classifier
Dynamic: description-content-type
Dynamic: license-file
Dynamic: requires-dist
Dynamic: requires-python
Dynamic: summary
